pygame_dps_core/__init__.py
pygame_dps_core/_conf.py
pygame_dps_core/const.py
pygame_dps_core/diagnostics.py
pygame_dps_core/game.py
pygame_dps_core/io.py
pygame_dps_core/keys.py
pygame_dps_core/logs.py
pygame_dps_core/scenes.py
pygame_dps_core/sprites.py
pygame_dps_core/text.py
pygame_dps_core/types.py
pygame_dps_core/ui.py
pygame_dps_core/utils.py
pygame_dps_core/version.py
pygame_dps_core-0.1.11.dist-info/METADATA
pygame_dps_core-0.1.11.dist-info/WHEEL
pygame_dps_core-0.1.11.dist-info/licenses/LICENSE
pygame_dps_core-0.1.11.dist-info/RECORD
