Metadata-Version: 2.4
Name: pygame-dps-core
Version: 0.1.11
Summary: Core modules for Pygame extension library
Project-URL: Homepage, https://github.com/dpsommer/pygame-dps-core
Project-URL: Issues, https://github.com/dpsommer/pygame-dps-core/issues
Author-email: Duncan Sommerville <duncan.sommerville@gmail.com>
License-Expression: MIT
License-File: LICENSE
Classifier: Operating System :: OS Independent
Classifier: Programming Language :: Python :: 3
Requires-Python: >=3.10
Requires-Dist: pygame==2.6.0
Requires-Dist: pyyaml==6.0.3
Provides-Extra: 2d
Requires-Dist: pygame-dps-2d; extra == '2d'
